{"1998": {"E2": {"Burnley": 55, "Northampton": 48, "Macclesfield": 43, "Bristol Rvs": 56, "Bournemouth": 76, "Blackpool": 56, "Walsall": 87, "Reading": 61, "Chesterfield": 64, "Notts County": 54, "Wrexham": 53, "Gillingham": 80, "Lincoln": 46, "Oldham": 51, "Millwall": 62, "Man City": 82, "Stoke": 69, "Luton": 58, "Colchester": 52, "York": 50, "Fulham": 101, "Preston": 79, "Wycombe": 51, "Wigan": 76}, "E1": {"Bradford": 87, "Bury": 47, "West Brom": 59, "Norwich": 62, "Huddersfield": 61, "Portsmouth": 47, "Tranmere": 56, "Crewe": 48, "Sheffield United": 67, "Bristol City": 42, "Ipswich": 86, "QPR": 47, "Oxford": 44, "Sunderland": 105, "Port Vale": 47, "Birmingham": 81, "Crystal Palace": 58, "Wolves": 73, "Grimsby": 61, "Barnsley": 59, "Stockport": 53, "Watford": 77, "Swindon": 50, "Bolton": 76}, "EC": {}, "E3": {"Chester": 57, "Rochdale": 54, "Swansea": 71, "Mansfield": 67, "Darlington": 65, "Hartlepool": 51, "Brighton": 55, "Torquay": 53, "Rotherham": 73, "Southend": 54, "Scarborough": 48, "Carlisle": 49, "Leyton Orient": 72, "Cardiff": 80, "Halifax": 66, "Scunthorpe": 74, "Cambridge": 81, "Barnet": 55, "Peterboro": 66, "Plymouth": 61, "Exeter": 63, "Hull": 53, "Brentford": 85, "Shrewsbury": 56}, "E0": {"Newcastle": 46, "Chelsea": 75, "Aston Villa": 55, "Tottenham": 47, "Man United": 79, "Leicester": 49, "Wimbledon": 42, "Liverpool": 54, "Charlton": 36, "Sheffield Weds": 46, "Derby": 52, "Leeds": 67, "Nott'm Forest": 30, "Middlesbrough": 51, "Everton": 43, "Southampton": 41, "Arsenal": 78, "Coventry": 42, "West Ham": 57, "Blackburn": 35}}, "1999": {"E2": {"Bury": 57, "Burnley": 88, "Bristol Rvs": 80, "Bournemouth": 57, "Blackpool": 41, "Preston": 95, "Cardiff": 44, "Reading": 62, "Chesterfield": 36, "Bristol City": 64, "Notts County": 65, "Wrexham": 62, "Gillingham": 85, "Oxford": 45, "Oldham": 60, "Millwall": 82, "Stoke": 82, "Wycombe": 61, "Scunthorpe": 39, "Cambridge": 48, "Colchester": 52, "Brentford": 52, "Luton": 61, "Wigan": 83}, "E1": {"Port Vale": 36, "West Brom": 49, "Norwich": 57, "Birmingham": 77, "Portsmouth": 51, "Walsall": 46, "Tranmere": 57, "Man City": 89, "Crewe": 51, "Sheffield United": 54, "Wolves": 74, "Blackburn": 62, "Fulham": 67, "QPR": 66, "Huddersfield": 74, "Ipswich": 87, "Grimsby": 51, "Nott'm Forest": 56, "Barnsley": 82, "Stockport": 54, "Crystal Palace": 54, "Swindon": 36, "Bolton": 76, "Charlton": 91}, "EC": {}, "E3": {"Cheltenham": 70, "Macclesfield": 65, "Chester": 39, "Rochdale": 66, "Swansea": 85, "Mansfield": 56, "Darlington": 79, "Hartlepool": 73, "York": 52, "Brighton": 67, "Northampton": 82, "Torquay": 69, "Rotherham": 84, "Southend": 56, "Lincoln": 59, "Carlisle": 39, "Halifax": 54, "Barnet": 75, "Peterboro": 78, "Plymouth": 66, "Exeter": 44, "Hull": 59, "Leyton Orient": 52, "Shrewsbury": 40}, "E0": {"Bradford": 36, "Newcastle": 52, "Chelsea": 65, "Aston Villa": 58, "Sunderland": 58, "Man United": 91, "Everton": 50, "Leicester": 55, "Liverpool": 67, "Wimbledon": 33, "Tottenham": 53, "Derby": 38, "Leeds": 69, "Watford": 24, "Middlesbrough": 52, "Sheffield Weds": 31, "Southampton": 44, "Arsenal": 73, "Coventry": 44, "West Ham": 55}}, "2010": {"E2": {"Huddersfield": 87, "Rochdale": 68, "Bristol Rvs": 45, "Bournemouth": 71, "Walsall": 48, "Hartlepool": 57, "Tranmere": 56, "Exeter": 70, "Brighton": 95, "Southampton": 92, "Notts County": 50, "Yeovil": 59, "Carlisle": 59, "Leyton Orient": 70, "Oldham": 56, "Milton Keynes Dons": 77, "Colchester": 62, "Dag and Red": 47, "Peterboro": 79, "Plymouth": 52, "Sheffield Weds": 58, "Swindon": 41, "Brentford": 61, "Charlton": 59}, "E1": {"Burnley": 68, "Norwich": 84, "Portsmouth": 58, "Swansea": 80, "Preston": 42, "Doncaster": 48, "Millwall": 67, "Derby": 49, "Leeds": 72, "Crystal Palace": 48, "Reading": 77, "Middlesbrough": 62, "Bristol City": 60, "QPR": 88, "Sheffield United": 42, "Leicester": 67, "Cardiff": 80, "Ipswich": 62, "Scunthorpe": 42, "Nott'm Forest": 75, "Barnsley": 56, "Watford": 61, "Hull": 65, "Coventry": 55}, "EC": {"Newport County": 69, "Forest Green": 46, "Kidderminster": 77, "Rushden & D": 62, "Southport": 46, "Mansfield": 61, "Darlington": 71, "Altrincham": 44, "Crawley Town": 105, "Kettering Town": 58, "Histon": 33, "Fleetwood Town": 78, "Grimsby": 62, "Tamworth": 49, "Hayes & Yeading": 51, "Barrow": 50, "Gateshead": 57, "Cambridge": 50, "Wrexham": 81, "Bath City": 63, "York": 71, "AFC Wimbledon": 90, "Luton": 84, "Eastbourne Borough": 39}, "E3": {"Bradford": 52, "Bury": 81, "Cheltenham": 52, "Macclesfield": 55, "Port Vale": 65, "Aldershot": 61, "Crewe": 65, "Chesterfield": 86, "Hereford": 53, "Torquay": 69, "Rotherham": 66, "Southend": 61, "Gillingham": 68, "Lincoln": 47, "Accrington": 73, "Oxford": 63, "Wycombe": 80, "Burton": 51, "Northampton": 52, "Stockport": 41, "Stevenage": 69, "Morecambe": 51, "Shrewsbury": 79, "Barnet": 48}, "E0": {"Newcastle": 46, "West Brom": 47, "Man United": 80, "Aston Villa": 48, "Stoke": 46, "Sunderland": 47, "Birmingham": 39, "Chelsea": 71, "Man City": 71, "Blackpool": 39, "Blackburn": 43, "Tottenham": 62, "Liverpool": 58, "Wolves": 40, "Everton": 54, "Arsenal": 68, "Wigan": 42, "Bolton": 46, "West Ham": 33, "Fulham": 49}}, "1997": {"E2": {"Burnley": 52, "Northampton": 71, "Bristol Rvs": 70, "Bournemouth": 66, "Blackpool": 62, "Preston": 59, "Wycombe": 60, "Watford": 88, "Walsall": 54, "Chesterfield": 65, "Bristol City": 85, "Fulham": 70, "Southend": 43, "Gillingham": 70, "Carlisle": 44, "Oldham": 61, "Millwall": 55, "Grimsby": 72, "Wrexham": 70, "Plymouth": 49, "York": 59, "Brentford": 50, "Luton": 57, "Wigan": 62}, "E1": {"Bradford": 57, "Bury": 52, "West Brom": 61, "Norwich": 55, "Birmingham": 74, "Portsmouth": 49, "Tranmere": 56, "Man City": 48, "Crewe": 59, "Sheffield United": 74, "Reading": 42, "Middlesbrough": 91, "Ipswich": 83, "QPR": 49, "Oxford": 58, "Sunderland": 90, "Port Vale": 49, "Huddersfield": 53, "Stoke": 46, "Wolves": 65, "Nott'm Forest": 94, "Stockport": 65, "Swindon": 52, "Charlton": 88}, "EC": {}, "E3": {"Macclesfield": 82, "Chester": 61, "Rochdale": 58, "Swansea": 50, "Mansfield": 65, "Doncaster": 20, "Darlington": 54, "Hartlepool": 59, "Brighton": 35, "Colchester": 74, "Torquay": 74, "Rotherham": 67, "Notts County": 99, "Scarborough": 72, "Lincoln": 75, "Cardiff": 50, "Scunthorpe": 69, "Cambridge": 60, "Barnet": 70, "Peterboro": 67, "Exeter": 60, "Hull": 41, "Leyton Orient": 69, "Shrewsbury": 61}, "E0": {"Newcastle": 44, "Chelsea": 63, "Aston Villa": 57, "Tottenham": 44, "Man United": 77, "Leicester": 53, "Wimbledon": 44, "Liverpool": 65, "Blackburn": 58, "Sheffield Weds": 44, "Derby": 55, "Barnsley": 35, "Crystal Palace": 33, "Everton": 40, "Southampton": 48, "Arsenal": 78, "Coventry": 52, "Bolton": 40, "West Ham": 56, "Leeds": 59}}, "2011": {"E2": {"Huddersfield": 81, "Bury": 56, "Milton Keynes Dons": 80, "Bournemouth": 58, "Preston": 54, "Hartlepool": 56, "Tranmere": 56, "Sheffield Weds": 93, "Sheffield United": 90, "Walsall": 50, "Chesterfield": 42, "Exeter": 42, "Notts County": 73, "Yeovil": 54, "Carlisle": 69, "Leyton Orient": 50, "Oldham": 54, "Wycombe": 43, "Scunthorpe": 52, "Colchester": 59, "Rochdale": 38, "Stevenage": 73, "Brentford": 67, "Charlton": 101}, "E1": {"Bristol City": 49, "Leicester": 66, "Birmingham": 76, "Portsmouth": 50, "Blackpool": 75, "Doncaster": 36, "Millwall": 57, "Derby": 64, "Leeds": 61, "Crystal Palace": 56, "Reading": 89, "Middlesbrough": 70, "Southampton": 88, "West Ham": 86, "Watford": 64, "Burnley": 62, "Cardiff": 75, "Ipswich": 61, "Nott'm Forest": 50, "Barnsley": 48, "Peterboro": 50, "Brighton": 66, "Hull": 68, "Coventry": 40}, "EC": {"Ebbsfleet": 54, "Braintree Town": 62, "Forest Green": 70, "Kidderminster": 76, "Southport": 76, "Mansfield": 89, "Darlington": 46, "Alfreton Town": 54, "Newport County": 47, "Wrexham": 98, "Fleetwood Town": 103, "Gateshead": 74, "Lincoln": 49, "Tamworth": 48, "Hayes & Yeading": 41, "Barrow": 60, "Grimsby": 70, "Cambridge": 71, "Kettering Town": 33, "Stockport": 51, "AFC Telford United": 46, "York": 83, "Luton": 81, "Bath City": 31}, "E3": {"Bradford": 50, "Port Vale": 69, "Cheltenham": 77, "Macclesfield": 37, "Morecambe": 56, "Bristol Rvs": 57, "Aldershot": 66, "Crewe": 72, "Accrington": 57, "Crawley Town": 84, "Torquay": 81, "Rotherham": 67, "Southend": 83, "Gillingham": 70, "Hereford": 44, "Oxford": 68, "Burton": 54, "Northampton": 48, "Dag and Red": 50, "Barnet": 46, "Plymouth": 46, "AFC Wimbledon": 54, "Swindon": 93, "Shrewsbury": 88}, "E0": {"Newcastle": 65, "West Brom": 47, "QPR": 37, "Aston Villa": 38, "Sunderland": 45, "Man United": 89, "Swansea": 47, "Chelsea": 64, "Man City": 89, "Stoke": 45, "Wolves": 25, "Tottenham": 69, "Liverpool": 52, "Everton": 56, "Norwich": 47, "Arsenal": 70, "Fulham": 52, "Bolton": 36, "Blackburn": 31, "Wigan": 43}}, "2005": {"E2": {"Bradford": 61, "Huddersfield": 73, "Port Vale": 60, "Milton Keynes Dons": 50, "Swansea": 71, "Bournemouth": 55, "Blackpool": 53, "Walsall": 47, "Hartlepool": 50, "Tranmere": 54, "Chesterfield": 56, "Bristol City": 65, "Rotherham": 52, "Southend": 82, "Gillingham": 60, "Yeovil": 56, "Oldham": 65, "Nott'm Forest": 69, "Scunthorpe": 60, "Colchester": 79, "Barnsley": 72, "Doncaster": 69, "Swindon": 48, "Brentford": 76}, "E1": {"Leicester": 54, "Norwich": 62, "Plymouth": 56, "Preston": 80, "Cardiff": 60, "Derby": 50, "Millwall": 40, "Crewe": 42, "Leeds": 78, "Sheffield United": 90, "Reading": 106, "Southampton": 58, "Brighton": 38, "Ipswich": 56, "Watford": 81, "QPR": 50, "Burnley": 54, "Stoke": 58, "Wolves": 67, "Sheffield Weds": 52, "Crystal Palace": 75, "Hull": 52, "Coventry": 63, "Luton": 61}, "EC": {"Forest Green": 38, "Kidderminster": 50, "Southport": 40, "Aldershot": 54, "Altrincham": 41, "Hereford": 80, "Crawley Town": 47, "Woking": 56, "Scarborough": 37, "Accrington": 91, "Canvey Island": 51, "Grays": 76, "Exeter": 63, "Tamworth": 38, "Gravesend": 49, "Burton": 60, "Halifax": 75, "Cambridge": 55, "Dag and Red": 58, "York": 63, "Stevenage": 69, "Morecambe": 74}, "E3": {"Bury": 53, "Cheltenham": 72, "Rushden & D": 45, "Chester": 54, "Bristol Rvs": 60, "Mansfield": 54, "Darlington": 63, "Northampton": 83, "Torquay": 52, "Notts County": 52, "Lincoln": 66, "Oxford": 49, "Macclesfield": 54, "Carlisle": 86, "Boston": 61, "Wycombe": 71, "Grimsby": 78, "Wrexham": 59, "Barnet": 54, "Peterboro": 62, "Rochdale": 56, "Leyton Orient": 81, "Shrewsbury": 61, "Stockport": 52}, "E0": {"Blackburn": 63, "Newcastle": 58, "West Brom": 30, "Chelsea": 91, "Aston Villa": 42, "Birmingham": 34, "Man United": 83, "Portsmouth": 38, "Sunderland": 15, "Man City": 43, "West Ham": 55, "Tottenham": 65, "Liverpool": 82, "Middlesbrough": 45, "Everton": 50, "Arsenal": 67, "Wigan": 51, "Bolton": 56, "Charlton": 47, "Fulham": 48}}, "2013": {"E2": {"Bradford": 59, "Port Vale": 61, "Milton Keynes Dons": 60, "Preston": 85, "Walsall": 58, "Tranmere": 47, "Crewe": 51, "Sheffield United": 67, "Bristol City": 58, "Crawley Town": 57, "Rotherham": 86, "Notts County": 50, "Gillingham": 53, "Coventry": 61, "Carlisle": 45, "Leyton Orient": 86, "Oldham": 56, "Wolves": 103, "Colchester": 53, "Peterboro": 74, "Stevenage": 42, "Swindon": 66, "Brentford": 94, "Shrewsbury": 42}, "E1": {"Huddersfield": 53, "Leeds": 57, "Birmingham": 44, "Bournemouth": 66, "Blackpool": 46, "Doncaster": 44, "Millwall": 48, "Derby": 85, "Watford": 60, "Reading": 71, "Middlesbrough": 64, "Blackburn": 70, "QPR": 80, "Yeovil": 37, "Burnley": 93, "Nott'm Forest": 65, "Ipswich": 68, "Leicester": 102, "Barnsley": 39, "Sheffield Weds": 53, "Brighton": 72, "Bolton": 59, "Charlton": 51, "Wigan": 73}, "EC": {"Braintree Town": 74, "Forest Green": 67, "Kidderminster": 72, "Macclesfield": 61, "Dartford": 44, "Southport": 53, "Nuneaton Town": 66, "Aldershot": 61, "Alfreton Town": 70, "Salisbury": 67, "Halifax": 77, "Grimsby": 78, "Lincoln": 65, "Hereford": 51, "Tamworth": 39, "Cambridge": 82, "Welling United": 60, "Gateshead": 79, "Chester": 51, "Wrexham": 59, "Woking": 68, "Barnet": 70, "Hyde United": 10, "Luton": 101}, "E3": {"Bury": 59, "Newport County": 58, "Cheltenham": 55, "Bristol Rvs": 50, "Mansfield": 60, "Hartlepool": 53, "York": 71, "Rochdale": 81, "Chesterfield": 84, "Accrington": 57, "Torquay": 45, "Morecambe": 54, "Fleetwood Town": 76, "Oxford": 62, "Southend": 72, "Wycombe": 50, "Burton": 72, "Northampton": 53, "Scunthorpe": 81, "Dag and Red": 60, "Plymouth": 60, "Exeter": 55, "AFC Wimbledon": 56, "Portsmouth": 59}, "E0": {"Newcastle": 49, "West Brom": 36, "Norwich": 33, "Sunderland": 38, "Man United": 64, "Hull": 37, "Swansea": 42, "Chelsea": 82, "Man City": 86, "Stoke": 50, "Cardiff": 30, "Tottenham": 69, "Liverpool": 84, "Crystal Palace": 45, "Southampton": 56, "Everton": 72, "Aston Villa": 38, "Arsenal": 79, "West Ham": 40, "Fulham": 32}}, "1994": {"E2": {"Bradford": 60, "Huddersfield": 81, "Birmingham": 89, "Chester": 29, "Plymouth": 46, "Swansea": 71, "Bournemouth": 50, "Blackpool": 64, "Crewe": 83, "Brighton": 59, "Rotherham": 56, "Oxford": 75, "Leyton Orient": 26, "Wycombe": 78, "Cardiff": 38, "Cambridge": 48, "Wrexham": 63, "Stockport": 65, "Peterboro": 60, "Bristol Rvs": 82, "York": 72, "Hull": 74, "Brentford": 85, "Shrewsbury": 53}, "E1": {"Port Vale": 58, "West Brom": 58, "Millwall": 62, "Portsmouth": 58, "Tranmere": 76, "Derby": 66, "Watford": 70, "Reading": 79, "Middlesbrough": 82, "Bristol City": 45, "Notts County": 40, "Southend": 62, "Luton": 58, "Sunderland": 54, "Oldham": 61, "Burnley": 46, "Stoke": 63, "Wolves": 76, "Grimsby": 65, "Barnsley": 72, "Sheffield United": 68, "Swindon": 48, "Bolton": 77, "Charlton": 59}, "EC": {}, "E3": {"Bury": 79, "Northampton": 44, "Scarborough": 34, "Rochdale": 50, "Preston": 67, "Doncaster": 61, "Darlington": 41, "Hartlepool": 43, "Mansfield": 65, "Walsall": 85, "Chesterfield": 81, "Torquay": 55, "Fulham": 62, "Gillingham": 41, "Lincoln": 56, "Hereford": 49, "Carlisle": 91, "Scunthorpe": 62, "Colchester": 58, "Barnet": 56, "Exeter": 34, "Wigan": 52}, "E0": {"Blackburn": 89, "Newcastle": 72, "Leeds": 73, "Norwich": 43, "Man United": 88, "Everton": 50, "Chelsea": 54, "Tottenham": 62, "Crystal Palace": 45, "Southampton": 54, "West Ham": 50, "QPR": 60, "Leicester": 29, "Man City": 49, "Liverpool": 74, "Ipswich": 27, "Nott'm Forest": 77, "Wimbledon": 56, "Sheffield Weds": 51, "Arsenal": 51, "Coventry": 50, "Aston Villa": 48}}, "1993": {"E2": {"Bradford": 70, "Port Vale": 88, "Huddersfield": 65, "Bristol Rvs": 67, "Swansea": 60, "Bournemouth": 57, "Blackpool": 53, "Hartlepool": 36, "York": 75, "Brighton": 59, "Reading": 89, "Rotherham": 58, "Fulham": 52, "Brentford": 58, "Burnley": 73, "Cardiff": 54, "Cambridge": 66, "Wrexham": 62, "Barnet": 31, "Plymouth": 85, "Exeter": 45, "Hull": 68, "Leyton Orient": 56, "Stockport": 85}, "E1": {"Bristol City": 64, "West Brom": 51, "Leicester": 73, "Birmingham": 51, "Portsmouth": 58, "Tranmere": 72, "Derby": 71, "Crystal Palace": 90, "Middlesbrough": 67, "Charlton": 65, "Notts County": 68, "Southend": 59, "Oxford": 49, "Sunderland": 65, "Millwall": 74, "Stoke": 67, "Wolves": 68, "Grimsby": 59, "Nott'm Forest": 83, "Barnsley": 55, "Peterboro": 37, "Watford": 54, "Bolton": 59, "Luton": 53}, "EC": {}, "E3": {"Bury": 53, "Northampton": 38, "Gillingham": 51, "Chester": 74, "Rochdale": 60, "Preston": 67, "Doncaster": 52, "Darlington": 41, "Crewe": 73, "Walsall": 60, "Chesterfield": 62, "Torquay": 67, "Scarborough": 53, "Lincoln": 47, "Hereford": 42, "Carlisle": 64, "Wycombe": 70, "Mansfield": 55, "Scunthorpe": 59, "Colchester": 49, "Shrewsbury": 79, "Wigan": 45}, "E0": {"Blackburn": 84, "Newcastle": 77, "Leeds": 70, "Aston Villa": 57, "Coventry": 56, "Man United": 92, "Chelsea": 51, "Tottenham": 45, "Sheffield United": 42, "Southampton": 43, "West Ham": 52, "Sheffield Weds": 64, "QPR": 60, "Oldham": 40, "Man City": 45, "Ipswich": 43, "Liverpool": 60, "Wimbledon": 65, "Everton": 44, "Arsenal": 71, "Swindon": 30, "Norwich": 53}}, "1996": {"E2": {"Bury": 84, "Burnley": 68, "Bristol Rvs": 56, "Bournemouth": 60, "Blackpool": 69, "Preston": 61, "Crewe": 73, "Watford": 67, "Walsall": 67, "Chesterfield": 68, "Bristol City": 73, "Rotherham": 35, "Notts County": 35, "Gillingham": 67, "Wycombe": 55, "Millwall": 61, "Wrexham": 69, "Stockport": 82, "Peterboro": 47, "Plymouth": 54, "York": 52, "Brentford": 74, "Luton": 78, "Shrewsbury": 46}, "E1": {"Bradford": 48, "Huddersfield": 54, "West Brom": 57, "Norwich": 63, "Port Vale": 67, "Portsmouth": 68, "Tranmere": 65, "Sheffield United": 73, "Reading": 57, "Ipswich": 74, "Southend": 39, "QPR": 66, "Oxford": 57, "Oldham": 43, "Birmingham": 66, "Man City": 61, "Stoke": 64, "Wolves": 76, "Grimsby": 46, "Barnsley": 80, "Crystal Palace": 71, "Swindon": 54, "Bolton": 98, "Charlton": 59}, "EC": {}, "E3": {"Northampton": 72, "Chester": 70, "Rochdale": 58, "Swansea": 71, "Mansfield": 64, "Doncaster": 52, "Darlington": 52, "Hartlepool": 51, "Brighton": 49, "Colchester": 68, "Torquay": 50, "Fulham": 87, "Scarborough": 63, "Lincoln": 66, "Hereford": 47, "Carlisle": 84, "Cardiff": 69, "Scunthorpe": 63, "Cambridge": 65, "Barnet": 58, "Exeter": 48, "Hull": 57, "Leyton Orient": 57, "Wigan": 87}, "E0": {"Newcastle": 68, "Leeds": 46, "Aston Villa": 61, "Sunderland": 40, "Man United": 75, "Liverpool": 68, "Leicester": 47, "Nott'm Forest": 34, "Blackburn": 42, "Tottenham": 46, "Derby": 46, "Wimbledon": 56, "Chelsea": 59, "Middlesbrough": 42, "Everton": 42, "Southampton": 41, "Arsenal": 68, "Coventry": 41, "West Ham": 42, "Sheffield Weds": 57}}, "2014": {"E2": {"Bradford": 65, "Port Vale": 54, "Milton Keynes Dons": 91, "Preston": 89, "Doncaster": 61, "Walsall": 59, "Crewe": 52, "Sheffield United": 71, "Chesterfield": 69, "Bristol City": 99, "Crawley Town": 50, "Notts County": 50, "Fleetwood Town": 63, "Gillingham": 62, "Coventry": 55, "Yeovil": 40, "Oldham": 57, "Scunthorpe": 56, "Colchester": 52, "Barnsley": 62, "Peterboro": 63, "Rochdale": 63, "Swindon": 79, "Leyton Orient": 49}, "E1": {"Huddersfield": 55, "Leeds": 56, "Norwich": 86, "Birmingham": 63, "Bournemouth": 90, "Blackpool": 26, "Derby": 77, "Brighton": 47, "Reading": 50, "Middlesbrough": 85, "Wolves": 78, "Blackburn": 67, "Fulham": 52, "Rotherham": 49, "Brentford": 78, "Millwall": 41, "Cardiff": 62, "Ipswich": 78, "Nott'm Forest": 59, "Sheffield Weds": 60, "Watford": 89, "Bolton": 51, "Charlton": 60, "Wigan": 39}, "EC": {"Braintree Town": 59, "Forest Green": 82, "Kidderminster": 57, "Macclesfield": 78, "Dartford": 39, "Bristol Rvs": 91, "Telford United": 39, "Eastleigh": 82, "Nuneaton Town": 39, "Aldershot": 53, "Alfreton Town": 45, "Altrincham": 56, "Torquay": 61, "Grimsby": 86, "Lincoln": 58, "Halifax": 66, "Gateshead": 66, "Chester": 63, "Wrexham": 66, "Woking": 76, "Barnet": 92, "Southport": 51, "Dover Athletic": 68, "Welling United": 45}, "E3": {"Bury": 85, "Newport County": 65, "Northampton": 61, "Plymouth": 71, "Cheltenham": 41, "Mansfield": 48, "Hartlepool": 45, "Tranmere": 39, "Exeter": 64, "Oxford": 61, "AFC Wimbledon": 58, "Southend": 84, "York": 52, "Accrington": 56, "Carlisle": 50, "Wycombe": 84, "Burton": 94, "Cambridge": 51, "Dag and Red": 59, "Portsmouth": 57, "Stevenage": 72, "Morecambe": 63, "Luton": 68, "Shrewsbury": 89}, "E0": {"Newcastle": 39, "West Brom": 44, "QPR": 30, "Aston Villa": 38, "Sunderland": 38, "Man United": 70, "Swansea": 56, "Leicester": 41, "Man City": 79, "Stoke": 54, "West Ham": 47, "Tottenham": 64, "Liverpool": 62, "Crystal Palace": 48, "Chelsea": 87, "Burnley": 33, "Everton": 47, "Southampton": 60, "Hull": 35, "Arsenal": 75}}, "2003": {"E2": {"Port Vale": 73, "Rushden & D": 48, "Plymouth": 90, "Bournemouth": 66, "Blackpool": 59, "Hartlepool": 73, "Tranmere": 67, "Brighton": 77, "Chesterfield": 51, "Bristol City": 82, "Notts County": 42, "QPR": 83, "Oldham": 57, "Wrexham": 60, "Wycombe": 37, "Grimsby": 50, "Colchester": 64, "Barnsley": 62, "Stockport": 52, "Peterboro": 52, "Sheffield Weds": 53, "Swindon": 73, "Brentford": 53, "Luton": 66}, "E1": {"Bradford": 36, "West Brom": 86, "Millwall": 69, "Norwich": 94, "Crewe": 53, "Preston": 59, "Walsall": 51, "Cardiff": 65, "Derby": 52, "Crystal Palace": 73, "Reading": 70, "Rotherham": 54, "Watford": 57, "Gillingham": 51, "Sunderland": 79, "West Ham": 74, "Burnley": 53, "Stoke": 66, "Ipswich": 73, "Nott'm Forest": 60, "Wimbledon": 29, "Sheffield United": 71, "Coventry": 65, "Wigan": 71}, "EC": {}, "E3": {"Huddersfield": 81, "Northampton": 75, "Kidderminster": 55, "Macclesfield": 52, "Bury": 56, "Bristol Rvs": 55, "Swansea": 59, "Mansfield": 75, "Doncaster": 92, "Darlington": 53, "Cheltenham": 56, "Boston": 59, "Southend": 54, "Lincoln": 74, "Oxford": 71, "Yeovil": 74, "Carlisle": 45, "Torquay": 81, "Scunthorpe": 49, "Cambridge": 56, "Rochdale": 50, "York": 44, "Hull": 88, "Leyton Orient": 53}, "E0": {"Newcastle": 56, "Leeds": 33, "Aston Villa": 56, "Birmingham": 50, "Man United": 75, "Portsmouth": 45, "Leicester": 33, "Man City": 41, "Wolves": 33, "Tottenham": 45, "Liverpool": 60, "Charlton": 53, "Chelsea": 79, "Middlesbrough": 48, "Everton": 39, "Southampton": 47, "Arsenal": 90, "Bolton": 53, "Blackburn": 44, "Fulham": 52}}, "2009": {"E2": {"Huddersfield": 80, "Leeds": 86, "Norwich": 95, "Bristol Rvs": 62, "Walsall": 62, "Hartlepool": 53, "Tranmere": 51, "Brighton": 59, "Southampton": 83, "Southend": 43, "Gillingham": 50, "Yeovil": 53, "Carlisle": 58, "Leyton Orient": 51, "Oldham": 52, "Millwall": 85, "Charlton": 84, "Colchester": 72, "Stockport": 25, "Milton Keynes Dons": 60, "Exeter": 51, "Swindon": 82, "Brentford": 62, "Wycombe": 45}, "E1": {"Newcastle": 102, "West Brom": 91, "Plymouth": 41, "Swansea": 69, "Preston": 54, "Doncaster": 60, "Blackpool": 70, "Derby": 56, "Crystal Palace": 59, "Reading": 63, "Middlesbrough": 62, "Bristol City": 63, "Watford": 54, "QPR": 57, "Leicester": 76, "Cardiff": 76, "Ipswich": 56, "Scunthorpe": 52, "Nott'm Forest": 79, "Barnsley": 54, "Peterboro": 34, "Sheffield Weds": 47, "Sheffield United": 65, "Coventry": 54}, "EC": {"Forest Green": 45, "Kidderminster": 57, "Rushden & D": 79, "Mansfield": 62, "York": 78, "Altrincham": 54, "Salisbury": 68, "Crawley Town": 66, "Histon": 46, "Wrexham": 58, "Ebbsfleet": 44, "Oxford": 86, "Grays": 28, "Tamworth": 49, "Hayes & Yeading": 48, "Barrow": 52, "Gateshead": 46, "Cambridge": 59, "Kettering Town": 66, "Stevenage": 99, "AFC Wimbledon": 64, "Luton": 88, "Eastbourne Borough": 46}, "E3": {"Bradford": 62, "Bury": 69, "Cheltenham": 48, "Macclesfield": 54, "Port Vale": 68, "Rochdale": 82, "Bournemouth": 83, "Darlington": 30, "Aldershot": 72, "Crewe": 55, "Chesterfield": 70, "Northampton": 67, "Torquay": 57, "Rotherham": 73, "Notts County": 93, "Lincoln": 50, "Accrington": 61, "Burton": 62, "Hereford": 59, "Grimsby": 44, "Dag and Red": 72, "Barnet": 48, "Morecambe": 73, "Shrewsbury": 63}, "E0": {"Tottenham": 70, "Burnley": 30, "Aston Villa": 64, "Sunderland": 44, "West Ham": 35, "Portsmouth": 28, "Chelsea": 86, "Man City": 67, "Stoke": 47, "Blackburn": 50, "Man United": 85, "Liverpool": 63, "Wolves": 38, "Everton": 61, "Arsenal": 75, "Fulham": 46, "Bolton": 39, "Hull": 30, "Birmingham": 50, "Wigan": 36}}, "2012": {"E2": {"Bury": 41, "Portsmouth": 42, "Bournemouth": 83, "Doncaster": 84, "Preston": 59, "Hartlepool": 41, "Tranmere": 67, "Crewe": 64, "Sheffield United": 75, "Walsall": 68, "Crawley Town": 68, "Notts County": 65, "Coventry": 65, "Yeovil": 77, "Carlisle": 55, "Brentford": 79, "Oldham": 51, "Scunthorpe": 48, "Colchester": 51, "Milton Keynes Dons": 70, "Stevenage": 54, "Swindon": 74, "Leyton Orient": 71, "Shrewsbury": 55}, "E1": {"Huddersfield": 58, "Leeds": 61, "Birmingham": 61, "Blackpool": 59, "Millwall": 56, "Derby": 61, "Brighton": 75, "Middlesbrough": 59, "Bristol City": 41, "Wolves": 51, "Blackburn": 58, "Watford": 77, "Leicester": 68, "Burnley": 61, "Cardiff": 87, "Ipswich": 60, "Nott'm Forest": 67, "Barnsley": 55, "Peterboro": 54, "Sheffield Weds": 58, "Crystal Palace": 72, "Hull": 79, "Bolton": 68, "Charlton": 65}, "EC": {"Braintree Town": 66, "Forest Green": 65, "Kidderminster": 93, "Macclesfield": 63, "Dartford": 66, "Southport": 54, "Mansfield": 95, "Nuneaton Town": 57, "Newport County": 85, "Woking": 62, "Wrexham": 80, "Gateshead": 55, "Lincoln": 56, "Hereford": 70, "Tamworth": 55, "Barrow": 46, "Ebbsfleet": 39, "Grimsby": 83, "Cambridge": 59, "Alfreton Town": 60, "Stockport": 50, "Telford United": 35, "Hyde United": 55, "Luton": 67}, "E3": {"Bradford": 69, "Port Vale": 78, "Northampton": 73, "Morecambe": 58, "Rochdale": 61, "Plymouth": 52, "Aldershot": 48, "Chesterfield": 67, "Cheltenham": 75, "Torquay": 53, "Rotherham": 79, "Fleetwood Town": 60, "Gillingham": 83, "Oxford": 65, "Southend": 61, "Wycombe": 60, "Burton": 76, "Accrington": 54, "Dag and Red": 51, "York": 55, "Barnet": 51, "Bristol Rvs": 60, "Exeter": 64, "AFC Wimbledon": 53}, "E0": {"Newcastle": 41, "West Brom": 49, "QPR": 25, "Norwich": 44, "Sunderland": 39, "Man United": 89, "Swansea": 46, "Chelsea": 75, "Man City": 78, "Stoke": 42, "Tottenham": 72, "Liverpool": 61, "Reading": 28, "Southampton": 41, "Everton": 63, "Aston Villa": 41, "Arsenal": 73, "Wigan": 36, "West Ham": 46, "Fulham": 43}}, "2002": {"E2": {"Huddersfield": 45, "Cheltenham": 48, "Port Vale": 53, "Plymouth": 65, "Mansfield": 44, "Blackpool": 58, "Tranmere": 80, "Crewe": 86, "Bristol City": 83, "Chesterfield": 50, "Northampton": 39, "Notts County": 55, "QPR": 83, "Wycombe": 52, "Cardiff": 81, "Luton": 65, "Colchester": 58, "Barnsley": 52, "Stockport": 55, "Peterboro": 58, "Swindon": 60, "Brentford": 54, "Oldham": 82, "Wigan": 100}, "E1": {"Bradford": 52, "Burnley": 55, "Norwich": 69, "Portsmouth": 98, "Preston": 61, "Walsall": 54, "Millwall": 66, "Derby": 52, "Crystal Palace": 59, "Reading": 79, "Brighton": 45, "Wolves": 76, "Rotherham": 59, "Watford": 60, "Gillingham": 62, "Leicester": 92, "Stoke": 50, "Ipswich": 70, "Grimsby": 39, "Nott'm Forest": 74, "Wimbledon": 65, "Sheffield Weds": 46, "Sheffield United": 80, "Coventry": 50}, "EC": {}, "E3": {"Bury": 70, "Kidderminster": 63, "Macclesfield": 54, "Rochdale": 52, "Swansea": 49, "Bournemouth": 74, "Darlington": 54, "Hartlepool": 85, "York": 66, "Boston": 58, "Southend": 54, "Lincoln": 70, "Oxford": 69, "Rushden & D": 87, "Carlisle": 49, "Torquay": 66, "Cambridge": 61, "Scunthorpe": 72, "Wrexham": 84, "Bristol Rvs": 51, "Exeter": 48, "Hull": 59, "Leyton Orient": 53, "Shrewsbury": 41}, "E0": {"Newcastle": 69, "West Brom": 26, "Leeds": 47, "Aston Villa": 45, "Sunderland": 19, "Man United": 83, "Chelsea": 67, "Man City": 51, "Blackburn": 60, "Tottenham": 50, "Liverpool": 64, "Middlesboro": 49, "Everton": 59, "Southampton": 52, "Arsenal": 78, "West Ham": 42, "Bolton": 44, "Charlton": 49, "Birmingham": 48, "Fulham": 48}}, "2008": {"E2": {"Huddersfield": 68, "Leicester": 96, "Cheltenham": 39, "Milton Keynes Dons": 87, "Walsall": 61, "Hartlepool": 50, "Tranmere": 74, "Crewe": 46, "Leeds": 84, "Brighton": 52, "Northampton": 49, "Southend": 71, "Hereford": 34, "Yeovil": 51, "Carlisle": 50, "Oldham": 65, "Millwall": 82, "Scunthorpe": 76, "Colchester": 63, "Stockport": 60, "Peterboro": 89, "Bristol Rvs": 63, "Swindon": 53, "Leyton Orient": 56}, "E1": {"Norwich": 46, "Birmingham": 83, "Plymouth": 51, "Swansea": 68, "Preston": 74, "Blackpool": 56, "Doncaster": 58, "Derby": 54, "Crystal Palace": 57, "Reading": 77, "Bristol City": 61, "Southampton": 45, "Wolves": 90, "Watford": 58, "QPR": 61, "Burnley": 76, "Cardiff": 74, "Ipswich": 66, "Nott'm Forest": 53, "Barnsley": 52, "Sheffield Weds": 61, "Sheffield United": 80, "Coventry": 54, "Charlton": 39}, "EC": {"Northwich": 43, "Salisbury": 55, "Kidderminster": 79, "Rushden & D": 63, "Mansfield": 66, "Weymouth": 43, "Stevenage": 81, "Altrincham": 56, "Forest Green": 52, "Crawley Town": 71, "Kettering Town": 76, "Torquay": 83, "Histon": 83, "Wrexham": 66, "Lewes": 24, "Oxford": 82, "Grays": 52, "Burton": 88, "Barrow": 51, "Ebbsfleet": 58, "Cambridge": 86, "Woking": 44, "York": 52, "Eastbourne Borough": 60}, "E3": {"Bradford": 67, "Bury": 78, "Macclesfield": 47, "Port Vale": 48, "Chester": 37, "Rochdale": 70, "Bournemouth": 63, "Darlington": 72, "Aldershot": 54, "Chesterfield": 63, "Rotherham": 75, "Notts County": 47, "Gillingham": 75, "Lincoln": 59, "Accrington": 50, "Wycombe": 78, "Grimsby": 41, "Dag and Red": 68, "Barnet": 48, "Exeter": 79, "Morecambe": 63, "Brentford": 85, "Luton": 56, "Shrewsbury": 69}, "E0": {"Newcastle": 34, "West Brom": 32, "Man United": 90, "Aston Villa": 62, "Sunderland": 36, "West Ham": 51, "Portsmouth": 41, "Chelsea": 83, "Man City": 50, "Stoke": 45, "Blackburn": 41, "Tottenham": 51, "Liverpool": 86, "Middlesbrough": 32, "Everton": 63, "Hull": 35, "Wigan": 45, "Bolton": 41, "Arsenal": 72, "Fulham": 53}}, "1995": {"E2": {"Bradford": 73, "Bristol Rvs": 70, "Swansea": 47, "Bournemouth": 58, "Blackpool": 82, "Walsall": 69, "Crewe": 73, "Brighton": 40, "Chesterfield": 72, "Bristol City": 60, "Rotherham": 56, "Notts County": 78, "Oxford": 83, "Carlisle": 49, "Wycombe": 60, "Burnley": 55, "Wrexham": 70, "Stockport": 70, "Peterboro": 52, "York": 52, "Hull": 31, "Swindon": 92, "Brentford": 58, "Shrewsbury": 53}, "E1": {"Huddersfield": 63, "West Brom": 60, "Millwall": 52, "Norwich": 57, "Birmingham": 58, "Portsmouth": 52, "Port Vale": 60, "Tranmere": 59, "Derby": 79, "Sheffield United": 62, "Reading": 56, "Wolves": 55, "Watford": 48, "Southend": 59, "Luton": 45, "Sunderland": 83, "Oldham": 56, "Leicester": 71, "Stoke": 73, "Ipswich": 69, "Grimsby": 56, "Barnsley": 60, "Crystal Palace": 75, "Charlton": 71}, "EC": {}, "E3": {"Bury": 79, "Northampton": 67, "Scarborough": 40, "Chester": 70, "Plymouth": 78, "Mansfield": 53, "Doncaster": 59, "Darlington": 78, "Hartlepool": 49, "Torquay": 29, "Fulham": 53, "Gillingham": 83, "Lincoln": 53, "Hereford": 74, "Leyton Orient": 47, "Cardiff": 45, "Scunthorpe": 60, "Cambridge": 54, "Colchester": 72, "Barnet": 70, "Rochdale": 55, "Exeter": 57, "Preston": 86, "Wigan": 70}, "E0": {"Newcastle": 78, "QPR": 33, "Aston Villa": 63, "Coventry": 38, "Man United": 82, "Chelsea": 50, "Man City": 38, "Nott'm Forest": 58, "Wimbledon": 41, "West Ham": 51, "Tottenham": 61, "Liverpool": 71, "Leeds": 43, "Middlesbrough": 43, "Everton": 61, "Southampton": 38, "Arsenal": 63, "Sheffield Weds": 40, "Bolton": 29, "Blackburn": 61}}, "2015": {"E2": {"Bradford": 80, "Port Vale": 65, "Burton": 85, "Bury": 60, "Rochdale": 69, "Doncaster": 46, "Walsall": 84, "Blackpool": 46, "Crewe": 34, "Sheffield United": 66, "Chesterfield": 53, "Fleetwood Town": 51, "Gillingham": 69, "Coventry": 69, "Southend": 59, "Oldham": 54, "Millwall": 81, "Scunthorpe": 74, "Colchester": 40, "Barnsley": 74, "Peterboro": 63, "Swindon": 59, "Shrewsbury": 50, "Wigan": 87}, "E1": {"Blackburn": 55, "Huddersfield": 51, "Leeds": 59, "Birmingham": 63, "Milton Keynes Dons": 39, "Preston": 62, "Derby": 78, "Brighton": 89, "Reading": 52, "Middlesbrough": 89, "Bristol City": 52, "Ipswich": 69, "Rotherham": 49, "Fulham": 51, "QPR": 60, "Brentford": 65, "Burnley": 93, "Cardiff": 68, "Wolves": 58, "Nott'm Forest": 55, "Sheffield Weds": 74, "Hull": 83, "Bolton": 30, "Charlton": 40}, "EC": {"Braintree Town": 81, "Forest Green": 89, "Kidderminster": 40, "Macclesfield": 66, "Chester": 54, "Southport": 55, "Eastleigh": 75, "Guiseley": 49, "Tranmere": 78, "Aldershot": 56, "Altrincham": 44, "Bromley": 60, "Boreham Wood": 50, "Cheltenham": 101, "Torquay": 51, "Gateshead": 67, "Lincoln": 61, "Barrow": 65, "Halifax": 48, "Grimsby": 80, "Wrexham": 69, "Woking": 61, "Dover Athletic": 80, "Welling United": 35}, "E3": {"Newport County": 43, "Northampton": 99, "Bristol Rvs": 85, "Mansfield": 64, "Hartlepool": 51, "Exeter": 64, "Accrington": 85, "Crawley Town": 47, "AFC Wimbledon": 75, "Notts County": 51, "York": 34, "Oxford": 86, "Yeovil": 48, "Carlisle": 67, "Wycombe": 64, "Cambridge": 68, "Dag and Red": 34, "Barnet": 62, "Plymouth": 81, "Stevenage": 48, "Morecambe": 46, "Leyton Orient": 69, "Luton": 66, "Portsmouth": 78}, "E0": {"Newcastle": 37, "West Brom": 43, "Chelsea": 50, "Aston Villa": 17, "Sunderland": 39, "Man United": 66, "Man City": 66, "Swansea": 47, "Leicester": 81, "Bournemouth": 42, "Stoke": 51, "Tottenham": 70, "Liverpool": 60, "Watford": 45, "Southampton": 63, "Everton": 47, "Norwich": 34, "Arsenal": 71, "Crystal Palace": 42, "West Ham": 62}}, "2006": {"E2": {"Bradford": 47, "Huddersfield": 59, "Northampton": 59, "Port Vale": 60, "Swansea": 72, "Bournemouth": 52, "Blackpool": 83, "Doncaster": 63, "Tranmere": 67, "Crewe": 60, "Brighton": 53, "Chesterfield": 47, "Bristol City": 85, "Rotherham": 48, "Gillingham": 59, "Yeovil": 79, "Carlisle": 68, "Brentford": 37, "Cheltenham": 54, "Millwall": 66, "Scunthorpe": 91, "Nott'm Forest": 82, "Leyton Orient": 51, "Oldham": 75}, "E1": {"West Brom": 76, "Leicester": 53, "Norwich": 57, "Birmingham": 86, "Plymouth": 67, "Preston": 74, "Cardiff": 64, "Derby": 84, "Leeds": 46, "Crystal Palace": 65, "Southampton": 75, "Wolves": 76, "Southend": 42, "QPR": 53, "Sunderland": 88, "Burnley": 57, "Stoke": 73, "Ipswich": 62, "Colchester": 69, "Barnsley": 50, "Sheffield Weds": 71, "Hull": 49, "Coventry": 56, "Luton": 40}, "EC": {"Northwich": 58, "Forest Green": 57, "Kidderminster": 63, "Rushden & D": 62, "Southport": 47, "Weymouth": 63, "Aldershot": 65, "Altrincham": 51, "Crawley Town": 63, "Stafford Rangers": 52, "Woking": 57, "York": 80, "Oxford": 81, "Grays": 52, "Exeter": 78, "Tamworth": 48, "Gravesend": 74, "Burton": 75, "Halifax": 55, "Cambridge": 55, "Dag and Red": 95, "Stevenage": 70, "Morecambe": 81, "St. Albans": 40}, "E3": {"Bury": 50, "Macclesfield": 48, "Chester": 53, "Bristol Rvs": 72, "Mansfield": 54, "Darlington": 65, "Hartlepool": 88, "Walsall": 89, "Hereford": 55, "Torquay": 35, "Notts County": 62, "Lincoln": 74, "Accrington": 50, "Milton Keynes Dons": 84, "Boston": 46, "Wycombe": 62, "Grimsby": 59, "Wrexham": 51, "Barnet": 59, "Peterboro": 65, "Rochdale": 66, "Swindon": 85, "Shrewsbury": 71, "Stockport": 71}, "E0": {"Newcastle": 43, "Aston Villa": 50, "Charlton": 34, "Man United": 89, "Portsmouth": 54, "Chelsea": 83, "Man City": 42, "West Ham": 41, "Tottenham": 60, "Liverpool": 68, "Watford": 28, "Reading": 55, "Middlesbrough": 46, "Everton": 58, "Sheffield United": 38, "Arsenal": 68, "Fulham": 39, "Bolton": 56, "Blackburn": 52, "Wigan": 38}}, "2000": {"E2": {"Bury": 58, "Northampton": 57, "Port Vale": 62, "Bristol Rvs": 51, "Swansea": 37, "Bournemouth": 73, "Walsall": 81, "Reading": 86, "Bristol City": 68, "Colchester": 57, "Rotherham": 91, "Notts County": 69, "Wrexham": 63, "Oxford": 27, "Oldham": 58, "Millwall": 93, "Stoke": 77, "Luton": 40, "Cambridge": 53, "Peterboro": 59, "Swindon": 52, "Brentford": 59, "Wycombe": 59, "Wigan": 75}, "E1": {"Huddersfield": 48, "West Brom": 74, "Norwich": 54, "Birmingham": 78, "Portsmouth": 49, "Preston": 78, "Tranmere": 38, "Crewe": 55, "Barnsley": 54, "Sheffield United": 68, "Blackburn": 91, "Watford": 69, "Fulham": 101, "Gillingham": 55, "QPR": 40, "Burnley": 72, "Wolves": 55, "Grimsby": 52, "Nott'm Forest": 68, "Wimbledon": 69, "Stockport": 51, "Sheffield Weds": 53, "Crystal Palace": 49, "Bolton": 87}, "EC": {}, "E3": {"Cheltenham": 68, "Kidderminster": 53, "Macclesfield": 56, "Rochdale": 71, "Mansfield": 58, "Blackpool": 72, "Darlington": 49, "Hartlepool": 77, "York": 52, "Brighton": 92, "Chesterfield": 89, "Torquay": 49, "Southend": 63, "Lincoln": 51, "Carlisle": 48, "Cardiff": 82, "Halifax": 47, "Scunthorpe": 65, "Barnet": 45, "Plymouth": 58, "Exeter": 50, "Hull": 74, "Leyton Orient": 75, "Shrewsbury": 55}, "E0": {"Bradford": 26, "Ipswich": 66, "Leicester": 48, "Aston Villa": 54, "Sunderland": 57, "Man United": 80, "Chelsea": 61, "Man City": 34, "Liverpool": 69, "Newcastle": 51, "West Ham": 42, "Tottenham": 49, "Derby": 42, "Leeds": 68, "Middlesbrough": 42, "Everton": 42, "Southampton": 52, "Arsenal": 70, "Coventry": 34, "Charlton": 52}}, "2004": {"E2": {"Bradford": 65, "Huddersfield": 70, "Port Vale": 56, "Milton Keynes Dons": 51, "Bournemouth": 70, "Blackpool": 57, "Walsall": 60, "Hartlepool": 71, "Tranmere": 79, "Doncaster": 66, "Chesterfield": 57, "Bristol City": 70, "Torquay": 51, "Oldham": 52, "Wrexham": 53, "Colchester": 59, "Barnsley": 61, "Stockport": 26, "Peterboro": 39, "Sheffield Weds": 72, "Hull": 86, "Swindon": 63, "Brentford": 75, "Luton": 98}, "E1": {"Leicester": 57, "Plymouth": 53, "Preston": 75, "Wolves": 66, "Stoke": 61, "Derby": 76, "Millwall": 66, "Crewe": 50, "Leeds": 60, "Sheffield United": 67, "Reading": 70, "Brighton": 51, "Ipswich": 85, "Rotherham": 29, "Gillingham": 50, "QPR": 62, "Sunderland": 94, "Burnley": 60, "Cardiff": 54, "West Ham": 73, "Nott'm Forest": 44, "Watford": 52, "Coventry": 52, "Wigan": 87}, "EC": {}, "E3": {"Bury": 58, "Cheltenham": 60, "Kidderminster": 38, "Macclesfield": 75, "Chester": 52, "Bristol Rvs": 60, "Swansea": 80, "Mansfield": 60, "Darlington": 72, "Northampton": 72, "Boston": 58, "Notts County": 52, "Southend": 78, "Grimsby": 58, "Lincoln": 72, "Oxford": 59, "Rushden & D": 44, "Yeovil": 83, "Wycombe": 65, "Scunthorpe": 80, "Cambridge": 40, "Rochdale": 66, "Leyton Orient": 63, "Shrewsbury": 49}, "E0": {"Newcastle": 44, "West Brom": 34, "Aston Villa": 47, "Birmingham": 45, "Man United": 77, "Portsmouth": 39, "Chelsea": 95, "Man City": 52, "Charlton": 46, "Tottenham": 52, "Liverpool": 58, "Crystal Palace": 33, "Middlesbrough": 55, "Everton": 61, "Southampton": 32, "Arsenal": 83, "Bolton": 58, "Blackburn": 42, "Norwich": 33, "Fulham": 44}}, "2001": {"E2": {"Huddersfield": 78, "Northampton": 49, "Port Vale": 58, "Bury": 44, "Bournemouth": 44, "Blackpool": 56, "Cardiff": 83, "Tranmere": 63, "Brighton": 90, "Reading": 84, "Chesterfield": 52, "Bristol City": 73, "Notts County": 50, "Wrexham": 43, "QPR": 71, "Wycombe": 64, "Stoke": 80, "Cambridge": 34, "Colchester": 57, "Peterboro": 55, "Swindon": 59, "Brentford": 83, "Oldham": 70, "Wigan": 64}, "E1": {"Bradford": 55, "West Brom": 89, "Burnley": 75, "Norwich": 75, "Birmingham": 76, "Barnsley": 48, "Preston": 72, "Walsall": 51, "Crewe": 49, "Watford": 59, "Crystal Palace": 66, "Rotherham": 49, "Gillingham": 64, "Millwall": 77, "Man City": 99, "Wolves": 86, "Grimsby": 50, "Nott'm Forest": 54, "Wimbledon": 67, "Stockport": 26, "Portsmouth": 53, "Sheffield Weds": 50, "Sheffield United": 60, "Coventry": 66}, "EC": {}, "E3": {"Cheltenham": 78, "Kidderminster": 66, "Macclesfield": 58, "Bristol Rvs": 45, "Swansea": 51, "Mansfield": 79, "Darlington": 56, "Hartlepool": 71, "York": 57, "Rochdale": 78, "Torquay": 51, "Southend": 58, "Lincoln": 46, "Oxford": 47, "Rushden & D": 73, "Carlisle": 52, "Halifax": 36, "Scunthorpe": 71, "Plymouth": 102, "Exeter": 55, "Hull": 61, "Leyton Orient": 52, "Luton": 97, "Shrewsbury": 70}, "E0": {"Blackburn": 46, "Newcastle": 71, "Leeds": 66, "Aston Villa": 50, "Sunderland": 40, "Chelsea": 64, "Leicester": 28, "Man United": 77, "Liverpool": 80, "Charlton": 44, "Tottenham": 50, "Derby": 30, "Middlesbrough": 45, "Everton": 43, "Southampton": 45, "Arsenal": 87, "Ipswich": 36, "Bolton": 40, "West Ham": 53, "Fulham": 44}}, "2007": {"E2": {"Huddersfield": 66, "Leeds": 91, "Cheltenham": 51, "Port Vale": 38, "Bristol Rvs": 53, "Swansea": 92, "Bournemouth": 58, "Doncaster": 80, "Walsall": 64, "Hartlepool": 54, "Tranmere": 65, "Crewe": 50, "Brighton": 69, "Northampton": 66, "Southend": 76, "Gillingham": 46, "Yeovil": 52, "Carlisle": 80, "Oldham": 67, "Millwall": 52, "Nott'm Forest": 82, "Swindon": 61, "Leyton Orient": 60, "Luton": 43}, "E1": {"West Brom": 81, "Leicester": 52, "Norwich": 55, "Plymouth": 64, "Preston": 56, "Blackpool": 54, "Stoke": 79, "Sheffield United": 66, "Bristol City": 74, "Southampton": 54, "Wolves": 70, "Watford": 70, "QPR": 58, "Burnley": 62, "Cardiff": 64, "Ipswich": 69, "Scunthorpe": 46, "Colchester": 38, "Barnsley": 55, "Sheffield Weds": 55, "Crystal Palace": 71, "Hull": 75, "Coventry": 53, "Charlton": 64}, "EC": {"Northwich": 44, "Salisbury": 68, "Kidderminster": 67, "Rushden & D": 59, "Weymouth": 46, "Torquay": 86, "Aldershot": 101, "Altrincham": 41, "Forest Green": 71, "Crawley Town": 66, "Stafford Rangers": 25, "Histon": 72, "Grays": 70, "York": 62, "Stevenage": 79, "Farsley": 39, "Oxford": 71, "Burton": 81, "Halifax": 52, "Ebbsfleet": 69, "Cambridge": 86, "Woking": 53, "Exeter": 83, "Droylsden": 24}, "E3": {"Bradford": 62, "Bury": 59, "Macclesfield": 50, "Chester": 47, "Milton Keynes Dons": 97, "Mansfield": 42, "Darlington": 78, "Chesterfield": 69, "Accrington": 51, "Rotherham": 74, "Notts County": 48, "Lincoln": 58, "Hereford": 88, "Wycombe": 78, "Grimsby": 55, "Wrexham": 40, "Dag and Red": 49, "Stockport": 82, "Peterboro": 92, "Rochdale": 80, "Morecambe": 60, "Brentford": 59, "Shrewsbury": 50, "Barnet": 60}, "E0": {"Newcastle": 43, "Man United": 87, "Aston Villa": 60, "Sunderland": 39, "Birmingham": 35, "Portsmouth": 57, "Chelsea": 85, "Man City": 55, "Derby": 11, "West Ham": 49, "Tottenham": 46, "Liverpool": 76, "Reading": 36, "Middlesbrough": 42, "Everton": 65, "Arsenal": 83, "Fulham": 36, "Bolton": 37, "Blackburn": 58, "Wigan": 40}}}